pyfetchmath/__init__.py
pyfetchmath/add.py
pyfetchmath/cli.py
pyfetchmath/init.py
pyfetchmath-0.1.0.dist-info/METADATA
pyfetchmath-0.1.0.dist-info/WHEEL
pyfetchmath-0.1.0.dist-info/entry_points.txt
pyfetchmath-0.1.0.dist-info/top_level.txt
pyfetchmath-0.1.0.dist-info/RECORD
