Metadata-Version: 2.4
Name: pyfetchmath
Version: 0.1.0
Summary: Fetch math utilities from a GitHub registry
Requires-Python: >=3.8
Requires-Dist: requests
